[
    {
        "id": "bcd117e9-a286-477b-980b-15a5399de451",
        "name": "Recipe 1",
        "description": "A generic description",
        "image": "https://source.unsplash.com/random",
        "average_time": "2238",
        "average_rate": "6",
        "ingredients": [
            "3034ee5d-7072-4e40-8cbb-ed8aa4d6f1df",
            "8287e154-daa4-444d-8eca-4d4155c724b2",
            "6ef34979-9123-4c30-8804-3b863c64c113"
        ],
        "steps": [
            {
                "name": "Step 1",
                "description": "A generic description"
            },
            {
                "name": "Step 2",
                "description": "A generic description"
            },
            {
                "name": "Step 3",
                "description": "A generic description"
            },
            {
                "name": "Step 4",
                "description": "A generic description"
            },
            {
                "name": "Step 5",
                "description": "A generic description"
            },
            {
                "name": "Step 6",
                "description": "A generic description"
            },
            {
                "name": "Step 7",
                "description": "A generic description"
            }
        ]
    },
    {
        "id": "024f890a-fdc7-49d7-8f2e-228a74d8a7bf",
        "name": "Recipe 2",
        "description": "A generic description",
        "image": "https://source.unsplash.com/random",
        "average_time": "4846",
        "average_rate": "6",
        "ingredients": [
            "6ef34979-9123-4c30-8804-3b863c64c113",
            "b3f13f2f-d2d4-4e15-8e06-5c9f822ec712",
            "5f073432-628d-40cd-b10e-e2d16b7cc6c4",
            "3034ee5d-7072-4e40-8cbb-ed8aa4d6f1df",
            "8287e154-daa4-444d-8eca-4d4155c724b2"
        ],
        "steps": [
            {
                "name": "Step 1",
                "description": "A generic description"
            },
            {
                "name": "Step 2",
                "description": "A generic description"
            },
            {
                "name": "Step 3",
                "description": "A generic description"
            },
            {
                "name": "Step 4",
                "description": "A generic description"
            },
            {
                "name": "Step 5",
                "description": "A generic description"
            },
            {
                "name": "Step 6",
                "description": "A generic description"
            },
            {
                "name": "Step 7",
                "description": "A generic description"
            },
            {
                "name": "Step 8",
                "description": "A generic description"
            },
            {
                "name": "Step 9",
                "description": "A generic description"
            },
            {
                "name": "Step 10",
                "description": "A generic description"
            }
        ]
    },
    {
        "id": "dd0e4a03-65f3-4623-bac1-e522996ab60e",
        "name": "Recipe 3",
        "description": "A generic description",
        "image": "https://source.unsplash.com/random",
        "average_time": "494",
        "average_rate": "0",
        "ingredients": [
            "6ef34979-9123-4c30-8804-3b863c64c113",
            "b3f13f2f-d2d4-4e15-8e06-5c9f822ec712",
            "5f073432-628d-40cd-b10e-e2d16b7cc6c4",
            "8287e154-daa4-444d-8eca-4d4155c724b2",
            "3034ee5d-7072-4e40-8cbb-ed8aa4d6f1df"
        ],
        "steps": [
            {
                "name": "Step 1",
                "description": "A generic description"
            },
            {
                "name": "Step 2",
                "description": "A generic description"
            },
            {
                "name": "Step 3",
                "description": "A generic description"
            },
            {
                "name": "Step 4",
                "description": "A generic description"
            }
        ]
    },
    {
        "id": "daac414b-98bf-4d93-85d9-9442f65e6185",
        "name": "Recipe 4",
        "description": "A generic description",
        "image": "https://source.unsplash.com/random",
        "average_time": "2155",
        "average_rate": "5",
        "ingredients": [
            "6ef34979-9123-4c30-8804-3b863c64c113",
            "e848b471-f922-4d23-a427-668c47ce1629",
            "5f073432-628d-40cd-b10e-e2d16b7cc6c4",
            "8287e154-daa4-444d-8eca-4d4155c724b2",
            "b3f13f2f-d2d4-4e15-8e06-5c9f822ec712",
            "3034ee5d-7072-4e40-8cbb-ed8aa4d6f1df"
        ],
        "steps": [
            {
                "name": "Step 1",
                "description": "A generic description"
            },
            {
                "name": "Step 2",
                "description": "A generic description"
            }
        ]
    },
    {
        "id": "03d93a5a-273b-4d79-95ee-d4ae6b5c1694",
        "name": "Recipe 5",
        "description": "A generic description",
        "image": "https://source.unsplash.com/random",
        "average_time": "3769",
        "average_rate": "4",
        "ingredients": [
            "5f073432-628d-40cd-b10e-e2d16b7cc6c4",
            "8287e154-daa4-444d-8eca-4d4155c724b2",
            "b3f13f2f-d2d4-4e15-8e06-5c9f822ec712",
            "6ef34979-9123-4c30-8804-3b863c64c113",
            "3034ee5d-7072-4e40-8cbb-ed8aa4d6f1df",
            "e848b471-f922-4d23-a427-668c47ce1629"
        ],
        "steps": [
            {
                "name": "Step 1",
                "description": "A generic description"
            },
            {
                "name": "Step 2",
                "description": "A generic description"
            },
            {
                "name": "Step 3",
                "description": "A generic description"
            },
            {
                "name": "Step 4",
                "description": "A generic description"
            },
            {
                "name": "Step 5",
                "description": "A generic description"
            },
            {
                "name": "Step 6",
                "description": "A generic description"
            },
            {
                "name": "Step 7",
                "description": "A generic description"
            },
            {
                "name": "Step 8",
                "description": "A generic description"
            },
            {
                "name": "Step 9",
                "description": "A generic description"
            }
        ]
    },
    {
        "id": "8905b3e0-54db-4d51-a941-e194a54197ad",
        "name": "Recipe 6",
        "description": "A generic description",
        "image": "https://source.unsplash.com/random",
        "average_time": "1982",
        "average_rate": "0",
        "ingredients": [
            "b3f13f2f-d2d4-4e15-8e06-5c9f822ec712",
            "8287e154-daa4-444d-8eca-4d4155c724b2",
            "5f073432-628d-40cd-b10e-e2d16b7cc6c4",
            "6ef34979-9123-4c30-8804-3b863c64c113"
        ],
        "steps": [
            {
                "name": "Step 1",
                "description": "A generic description"
            },
            {
                "name": "Step 2",
                "description": "A generic description"
            },
            {
                "name": "Step 3",
                "description": "A generic description"
            },
            {
                "name": "Step 4",
                "description": "A generic description"
            },
            {
                "name": "Step 5",
                "description": "A generic description"
            },
            {
                "name": "Step 6",
                "description": "A generic description"
            }
        ]
    },
    {
        "id": "4e47f914-5a46-49cc-bae9-bb3e34331af4",
        "name": "Recipe 7",
        "description": "A generic description",
        "image": "https://source.unsplash.com/random",
        "average_time": "2367",
        "average_rate": "1",
        "ingredients": [
            "b3f13f2f-d2d4-4e15-8e06-5c9f822ec712",
            "e848b471-f922-4d23-a427-668c47ce1629",
            "6ef34979-9123-4c30-8804-3b863c64c113"
        ],
        "steps": [
            {
                "name": "Step 1",
                "description": "A generic description"
            },
            {
                "name": "Step 2",
                "description": "A generic description"
            },
            {
                "name": "Step 3",
                "description": "A generic description"
            }
        ]
    },
    {
        "id": "5d27a954-eca9-4319-9f9b-83d0de528fb6",
        "name": "Recipe 8",
        "description": "A generic description",
        "image": "https://source.unsplash.com/random",
        "average_time": "4583",
        "average_rate": "6",
        "ingredients": [
            "8287e154-daa4-444d-8eca-4d4155c724b2",
            "e848b471-f922-4d23-a427-668c47ce1629",
            "3034ee5d-7072-4e40-8cbb-ed8aa4d6f1df",
            "5f073432-628d-40cd-b10e-e2d16b7cc6c4",
            "6ef34979-9123-4c30-8804-3b863c64c113",
            "b3f13f2f-d2d4-4e15-8e06-5c9f822ec712"
        ],
        "steps": [
            {
                "name": "Step 1",
                "description": "A generic description"
            },
            {
                "name": "Step 2",
                "description": "A generic description"
            },
            {
                "name": "Step 3",
                "description": "A generic description"
            },
            {
                "name": "Step 4",
                "description": "A generic description"
            }
        ]
    },
    {
        "id": "e5755d82-3dfb-43a5-b68e-b52cb5f11eb6",
        "name": "Recipe 9",
        "description": "A generic description",
        "image": "https://source.unsplash.com/random",
        "average_time": "2538",
        "average_rate": "6",
        "ingredients": [
            "5f073432-628d-40cd-b10e-e2d16b7cc6c4",
            "6ef34979-9123-4c30-8804-3b863c64c113",
            "e848b471-f922-4d23-a427-668c47ce1629",
            "8287e154-daa4-444d-8eca-4d4155c724b2",
            "b3f13f2f-d2d4-4e15-8e06-5c9f822ec712",
            "3034ee5d-7072-4e40-8cbb-ed8aa4d6f1df"
        ],
        "steps": [
            {
                "name": "Step 1",
                "description": "A generic description"
            },
            {
                "name": "Step 2",
                "description": "A generic description"
            }
        ]
    },
    {
        "id": "1fc4a0a9-2568-42fd-b28b-4168e5024060",
        "name": "Recipe 10",
        "description": "A generic description",
        "image": "https://source.unsplash.com/random",
        "average_time": "3125",
        "average_rate": "5",
        "ingredients": [
            "6ef34979-9123-4c30-8804-3b863c64c113",
            "e848b471-f922-4d23-a427-668c47ce1629",
            "3034ee5d-7072-4e40-8cbb-ed8aa4d6f1df",
            "5f073432-628d-40cd-b10e-e2d16b7cc6c4",
            "b3f13f2f-d2d4-4e15-8e06-5c9f822ec712"
        ],
        "steps": [
            {
                "name": "Step 1",
                "description": "A generic description"
            },
            {
                "name": "Step 2",
                "description": "A generic description"
            },
            {
                "name": "Step 3",
                "description": "A generic description"
            },
            {
                "name": "Step 4",
                "description": "A generic description"
            },
            {
                "name": "Step 5",
                "description": "A generic description"
            }
        ]
    },
    {
        "id": "c095bba7-35e4-4be0-b23d-e54a1748afd6",
        "name": "Recipe 11",
        "description": "A generic description",
        "image": "https://source.unsplash.com/random",
        "average_time": "3720",
        "average_rate": "0",
        "ingredients": [
            "8287e154-daa4-444d-8eca-4d4155c724b2",
            "e848b471-f922-4d23-a427-668c47ce1629",
            "5f073432-628d-40cd-b10e-e2d16b7cc6c4",
            "b3f13f2f-d2d4-4e15-8e06-5c9f822ec712"
        ],
        "steps": [
            {
                "name": "Step 1",
                "description": "A generic description"
            },
            {
                "name": "Step 2",
                "description": "A generic description"
            },
            {
                "name": "Step 3",
                "description": "A generic description"
            },
            {
                "name": "Step 4",
                "description": "A generic description"
            },
            {
                "name": "Step 5",
                "description": "A generic description"
            }
        ]
    },
    {
        "id": "e722d779-d006-4330-83ce-eaa9a86f957d",
        "name": "Recipe 12",
        "description": "A generic description",
        "image": "https://source.unsplash.com/random",
        "average_time": "3903",
        "average_rate": "4",
        "ingredients": [
            "8287e154-daa4-444d-8eca-4d4155c724b2",
            "b3f13f2f-d2d4-4e15-8e06-5c9f822ec712",
            "5f073432-628d-40cd-b10e-e2d16b7cc6c4"
        ],
        "steps": [
            {
                "name": "Step 1",
                "description": "A generic description"
            },
            {
                "name": "Step 2",
                "description": "A generic description"
            }
        ]
    },
    {
        "id": "6f2f81d9-1a0c-44ed-9250-4dea466b36e9",
        "name": "Recipe 13",
        "description": "A generic description",
        "image": "https://source.unsplash.com/random",
        "average_time": "3671",
        "average_rate": "4",
        "ingredients": [
            "6ef34979-9123-4c30-8804-3b863c64c113",
            "b3f13f2f-d2d4-4e15-8e06-5c9f822ec712",
            "8287e154-daa4-444d-8eca-4d4155c724b2",
            "5f073432-628d-40cd-b10e-e2d16b7cc6c4"
        ],
        "steps": [
            {
                "name": "Step 1",
                "description": "A generic description"
            },
            {
                "name": "Step 2",
                "description": "A generic description"
            },
            {
                "name": "Step 3",
                "description": "A generic description"
            },
            {
                "name": "Step 4",
                "description": "A generic description"
            },
            {
                "name": "Step 5",
                "description": "A generic description"
            },
            {
                "name": "Step 6",
                "description": "A generic description"
            },
            {
                "name": "Step 7",
                "description": "A generic description"
            }
        ]
    },
    {
        "id": "bf4cc764-a401-4708-a798-129192abcb0b",
        "name": "Recipe 14",
        "description": "A generic description",
        "image": "https://source.unsplash.com/random",
        "average_time": "1403",
        "average_rate": "3",
        "ingredients": [
            "b3f13f2f-d2d4-4e15-8e06-5c9f822ec712",
            "3034ee5d-7072-4e40-8cbb-ed8aa4d6f1df",
            "5f073432-628d-40cd-b10e-e2d16b7cc6c4",
            "e848b471-f922-4d23-a427-668c47ce1629",
            "8287e154-daa4-444d-8eca-4d4155c724b2"
        ],
        "steps": [
            {
                "name": "Step 1",
                "description": "A generic description"
            },
            {
                "name": "Step 2",
                "description": "A generic description"
            },
            {
                "name": "Step 3",
                "description": "A generic description"
            }
        ]
    },
    {
        "id": "3fa6dbe8-c004-4924-91ca-b22f31b82a9f",
        "name": "Recipe 15",
        "description": "A generic description",
        "image": "https://source.unsplash.com/random",
        "average_time": "2475",
        "average_rate": "6",
        "ingredients": [
            "6ef34979-9123-4c30-8804-3b863c64c113",
            "3034ee5d-7072-4e40-8cbb-ed8aa4d6f1df",
            "b3f13f2f-d2d4-4e15-8e06-5c9f822ec712",
            "e848b471-f922-4d23-a427-668c47ce1629",
            "8287e154-daa4-444d-8eca-4d4155c724b2",
            "5f073432-628d-40cd-b10e-e2d16b7cc6c4"
        ],
        "steps": [
            {
                "name": "Step 1",
                "description": "A generic description"
            },
            {
                "name": "Step 2",
                "description": "A generic description"
            },
            {
                "name": "Step 3",
                "description": "A generic description"
            }
        ]
    },
    {
        "id": "a8d9cbaf-f5a4-4b65-a425-ef9a71fd6746",
        "name": "Recipe 16",
        "description": "A generic description",
        "image": "https://source.unsplash.com/random",
        "average_time": "1596",
        "average_rate": "6",
        "ingredients": [
            "e848b471-f922-4d23-a427-668c47ce1629",
            "8287e154-daa4-444d-8eca-4d4155c724b2",
            "3034ee5d-7072-4e40-8cbb-ed8aa4d6f1df",
            "6ef34979-9123-4c30-8804-3b863c64c113"
        ],
        "steps": [
            {
                "name": "Step 1",
                "description": "A generic description"
            },
            {
                "name": "Step 2",
                "description": "A generic description"
            },
            {
                "name": "Step 3",
                "description": "A generic description"
            },
            {
                "name": "Step 4",
                "description": "A generic description"
            },
            {
                "name": "Step 5",
                "description": "A generic description"
            },
            {
                "name": "Step 6",
                "description": "A generic description"
            },
            {
                "name": "Step 7",
                "description": "A generic description"
            },
            {
                "name": "Step 8",
                "description": "A generic description"
            },
            {
                "name": "Step 9",
                "description": "A generic description"
            },
            {
                "name": "Step 10",
                "description": "A generic description"
            }
        ]
    },
    {
        "id": "7e73278a-c73b-40b0-b73c-42d67e962dae",
        "name": "Recipe 17",
        "description": "A generic description",
        "image": "https://source.unsplash.com/random",
        "average_time": "1351",
        "average_rate": "6",
        "ingredients": [
            "e848b471-f922-4d23-a427-668c47ce1629",
            "3034ee5d-7072-4e40-8cbb-ed8aa4d6f1df",
            "8287e154-daa4-444d-8eca-4d4155c724b2",
            "5f073432-628d-40cd-b10e-e2d16b7cc6c4"
        ],
        "steps": [
            {
                "name": "Step 1",
                "description": "A generic description"
            },
            {
                "name": "Step 2",
                "description": "A generic description"
            },
            {
                "name": "Step 3",
                "description": "A generic description"
            },
            {
                "name": "Step 4",
                "description": "A generic description"
            },
            {
                "name": "Step 5",
                "description": "A generic description"
            },
            {
                "name": "Step 6",
                "description": "A generic description"
            },
            {
                "name": "Step 7",
                "description": "A generic description"
            },
            {
                "name": "Step 8",
                "description": "A generic description"
            }
        ]
    },
    {
        "id": "ab6eb8e5-13d6-43d2-9286-d9f809017784",
        "name": "Recipe 18",
        "description": "A generic description",
        "image": "https://source.unsplash.com/random",
        "average_time": "460",
        "average_rate": "2",
        "ingredients": [
            "5f073432-628d-40cd-b10e-e2d16b7cc6c4",
            "3034ee5d-7072-4e40-8cbb-ed8aa4d6f1df",
            "e848b471-f922-4d23-a427-668c47ce1629",
            "6ef34979-9123-4c30-8804-3b863c64c113",
            "8287e154-daa4-444d-8eca-4d4155c724b2"
        ],
        "steps": [
            {
                "name": "Step 1",
                "description": "A generic description"
            },
            {
                "name": "Step 2",
                "description": "A generic description"
            },
            {
                "name": "Step 3",
                "description": "A generic description"
            },
            {
                "name": "Step 4",
                "description": "A generic description"
            },
            {
                "name": "Step 5",
                "description": "A generic description"
            },
            {
                "name": "Step 6",
                "description": "A generic description"
            },
            {
                "name": "Step 7",
                "description": "A generic description"
            }
        ]
    },
    {
        "id": "a15c89d4-bb8a-4ea0-b0c3-ca3387f6237d",
        "name": "Recipe 19",
        "description": "A generic description",
        "image": "https://source.unsplash.com/random",
        "average_time": "2266",
        "average_rate": "1",
        "ingredients": [
            "b3f13f2f-d2d4-4e15-8e06-5c9f822ec712",
            "6ef34979-9123-4c30-8804-3b863c64c113",
            "8287e154-daa4-444d-8eca-4d4155c724b2",
            "e848b471-f922-4d23-a427-668c47ce1629",
            "5f073432-628d-40cd-b10e-e2d16b7cc6c4"
        ],
        "steps": [
            {
                "name": "Step 1",
                "description": "A generic description"
            },
            {
                "name": "Step 2",
                "description": "A generic description"
            },
            {
                "name": "Step 3",
                "description": "A generic description"
            },
            {
                "name": "Step 4",
                "description": "A generic description"
            },
            {
                "name": "Step 5",
                "description": "A generic description"
            },
            {
                "name": "Step 6",
                "description": "A generic description"
            },
            {
                "name": "Step 7",
                "description": "A generic description"
            },
            {
                "name": "Step 8",
                "description": "A generic description"
            },
            {
                "name": "Step 9",
                "description": "A generic description"
            }
        ]
    },
    {
        "id": "16517cfe-82f4-4645-995a-881afc0d44a6",
        "name": "Recipe 20",
        "description": "A generic description",
        "image": "https://source.unsplash.com/random",
        "average_time": "3468",
        "average_rate": "3",
        "ingredients": [
            "3034ee5d-7072-4e40-8cbb-ed8aa4d6f1df",
            "8287e154-daa4-444d-8eca-4d4155c724b2",
            "5f073432-628d-40cd-b10e-e2d16b7cc6c4",
            "6ef34979-9123-4c30-8804-3b863c64c113",
            "b3f13f2f-d2d4-4e15-8e06-5c9f822ec712"
        ],
        "steps": [
            {
                "name": "Step 1",
                "description": "A generic description"
            },
            {
                "name": "Step 2",
                "description": "A generic description"
            },
            {
                "name": "Step 3",
                "description": "A generic description"
            },
            {
                "name": "Step 4",
                "description": "A generic description"
            },
            {
                "name": "Step 5",
                "description": "A generic description"
            },
            {
                "name": "Step 6",
                "description": "A generic description"
            },
            {
                "name": "Step 7",
                "description": "A generic description"
            }
        ]
    },
    {
        "id": "1c3f78ed-cf36-446e-85ca-4452c6d37ddc",
        "name": "Recipe 21",
        "description": "A generic description",
        "image": "https://source.unsplash.com/random",
        "average_time": "2425",
        "average_rate": "1",
        "ingredients": [
            "6ef34979-9123-4c30-8804-3b863c64c113",
            "b3f13f2f-d2d4-4e15-8e06-5c9f822ec712",
            "8287e154-daa4-444d-8eca-4d4155c724b2",
            "5f073432-628d-40cd-b10e-e2d16b7cc6c4",
            "3034ee5d-7072-4e40-8cbb-ed8aa4d6f1df",
            "e848b471-f922-4d23-a427-668c47ce1629"
        ],
        "steps": [
            {
                "name": "Step 1",
                "description": "A generic description"
            },
            {
                "name": "Step 2",
                "description": "A generic description"
            }
        ]
    },
    {
        "id": "372e223a-a199-463e-95fe-539b0da68486",
        "name": "Recipe 22",
        "description": "A generic description",
        "image": "https://source.unsplash.com/random",
        "average_time": "3379",
        "average_rate": "3",
        "ingredients": [
            "e848b471-f922-4d23-a427-668c47ce1629",
            "6ef34979-9123-4c30-8804-3b863c64c113",
            "8287e154-daa4-444d-8eca-4d4155c724b2",
            "3034ee5d-7072-4e40-8cbb-ed8aa4d6f1df",
            "b3f13f2f-d2d4-4e15-8e06-5c9f822ec712",
            "5f073432-628d-40cd-b10e-e2d16b7cc6c4"
        ],
        "steps": [
            {
                "name": "Step 1",
                "description": "A generic description"
            },
            {
                "name": "Step 2",
                "description": "A generic description"
            },
            {
                "name": "Step 3",
                "description": "A generic description"
            },
            {
                "name": "Step 4",
                "description": "A generic description"
            },
            {
                "name": "Step 5",
                "description": "A generic description"
            },
            {
                "name": "Step 6",
                "description": "A generic description"
            },
            {
                "name": "Step 7",
                "description": "A generic description"
            },
            {
                "name": "Step 8",
                "description": "A generic description"
            }
        ]
    },
    {
        "id": "91bd4850-a05c-4858-9a2e-210b297a2701",
        "name": "Recipe 23",
        "description": "A generic description",
        "image": "https://source.unsplash.com/random",
        "average_time": "1502",
        "average_rate": "5",
        "ingredients": [
            "6ef34979-9123-4c30-8804-3b863c64c113",
            "b3f13f2f-d2d4-4e15-8e06-5c9f822ec712",
            "5f073432-628d-40cd-b10e-e2d16b7cc6c4",
            "8287e154-daa4-444d-8eca-4d4155c724b2"
        ],
        "steps": [
            {
                "name": "Step 1",
                "description": "A generic description"
            },
            {
                "name": "Step 2",
                "description": "A generic description"
            },
            {
                "name": "Step 3",
                "description": "A generic description"
            },
            {
                "name": "Step 4",
                "description": "A generic description"
            },
            {
                "name": "Step 5",
                "description": "A generic description"
            },
            {
                "name": "Step 6",
                "description": "A generic description"
            },
            {
                "name": "Step 7",
                "description": "A generic description"
            },
            {
                "name": "Step 8",
                "description": "A generic description"
            },
            {
                "name": "Step 9",
                "description": "A generic description"
            }
        ]
    },
    {
        "id": "d4816949-9ecc-4fc2-91bb-b29bb041267b",
        "name": "Recipe 24",
        "description": "A generic description",
        "image": "https://source.unsplash.com/random",
        "average_time": "3403",
        "average_rate": "1",
        "ingredients": [
            "e848b471-f922-4d23-a427-668c47ce1629",
            "b3f13f2f-d2d4-4e15-8e06-5c9f822ec712",
            "8287e154-daa4-444d-8eca-4d4155c724b2"
        ],
        "steps": [
            {
                "name": "Step 1",
                "description": "A generic description"
            },
            {
                "name": "Step 2",
                "description": "A generic description"
            },
            {
                "name": "Step 3",
                "description": "A generic description"
            },
            {
                "name": "Step 4",
                "description": "A generic description"
            },
            {
                "name": "Step 5",
                "description": "A generic description"
            },
            {
                "name": "Step 6",
                "description": "A generic description"
            },
            {
                "name": "Step 7",
                "description": "A generic description"
            },
            {
                "name": "Step 8",
                "description": "A generic description"
            }
        ]
    },
    {
        "id": "9a18e911-2e7c-4690-9962-8a335675da80",
        "name": "Recipe 25",
        "description": "A generic description",
        "image": "https://source.unsplash.com/random",
        "average_time": "4776",
        "average_rate": "4",
        "ingredients": [
            "5f073432-628d-40cd-b10e-e2d16b7cc6c4",
            "8287e154-daa4-444d-8eca-4d4155c724b2",
            "e848b471-f922-4d23-a427-668c47ce1629",
            "b3f13f2f-d2d4-4e15-8e06-5c9f822ec712",
            "3034ee5d-7072-4e40-8cbb-ed8aa4d6f1df",
            "6ef34979-9123-4c30-8804-3b863c64c113"
        ],
        "steps": [
            {
                "name": "Step 1",
                "description": "A generic description"
            },
            {
                "name": "Step 2",
                "description": "A generic description"
            },
            {
                "name": "Step 3",
                "description": "A generic description"
            },
            {
                "name": "Step 4",
                "description": "A generic description"
            },
            {
                "name": "Step 5",
                "description": "A generic description"
            }
        ]
    },
    {
        "id": "dfb32a99-ffd5-489a-8984-ef2162ac192e",
        "name": "Recipe 26",
        "description": "A generic description",
        "image": "https://source.unsplash.com/random",
        "average_time": "2117",
        "average_rate": "4",
        "ingredients": [
            "b3f13f2f-d2d4-4e15-8e06-5c9f822ec712",
            "5f073432-628d-40cd-b10e-e2d16b7cc6c4"
        ],
        "steps": [
            {
                "name": "Step 1",
                "description": "A generic description"
            },
            {
                "name": "Step 2",
                "description": "A generic description"
            },
            {
                "name": "Step 3",
                "description": "A generic description"
            },
            {
                "name": "Step 4",
                "description": "A generic description"
            },
            {
                "name": "Step 5",
                "description": "A generic description"
            },
            {
                "name": "Step 6",
                "description": "A generic description"
            },
            {
                "name": "Step 7",
                "description": "A generic description"
            }
        ]
    },
    {
        "id": "42d656ad-3b9f-4016-b137-367834e1b246",
        "name": "Recipe 27",
        "description": "A generic description",
        "image": "https://source.unsplash.com/random",
        "average_time": "1106",
        "average_rate": "4",
        "ingredients": [
            "e848b471-f922-4d23-a427-668c47ce1629",
            "6ef34979-9123-4c30-8804-3b863c64c113",
            "5f073432-628d-40cd-b10e-e2d16b7cc6c4",
            "8287e154-daa4-444d-8eca-4d4155c724b2"
        ],
        "steps": [
            {
                "name": "Step 1",
                "description": "A generic description"
            },
            {
                "name": "Step 2",
                "description": "A generic description"
            },
            {
                "name": "Step 3",
                "description": "A generic description"
            },
            {
                "name": "Step 4",
                "description": "A generic description"
            },
            {
                "name": "Step 5",
                "description": "A generic description"
            },
            {
                "name": "Step 6",
                "description": "A generic description"
            },
            {
                "name": "Step 7",
                "description": "A generic description"
            },
            {
                "name": "Step 8",
                "description": "A generic description"
            },
            {
                "name": "Step 9",
                "description": "A generic description"
            }
        ]
    },
    {
        "id": "0ebc0814-d263-4c59-9df9-c005946e873c",
        "name": "Recipe 28",
        "description": "A generic description",
        "image": "https://source.unsplash.com/random",
        "average_time": "4669",
        "average_rate": "3",
        "ingredients": [
            "5f073432-628d-40cd-b10e-e2d16b7cc6c4",
            "b3f13f2f-d2d4-4e15-8e06-5c9f822ec712",
            "3034ee5d-7072-4e40-8cbb-ed8aa4d6f1df",
            "8287e154-daa4-444d-8eca-4d4155c724b2"
        ],
        "steps": [
            {
                "name": "Step 1",
                "description": "A generic description"
            },
            {
                "name": "Step 2",
                "description": "A generic description"
            },
            {
                "name": "Step 3",
                "description": "A generic description"
            },
            {
                "name": "Step 4",
                "description": "A generic description"
            },
            {
                "name": "Step 5",
                "description": "A generic description"
            }
        ]
    },
    {
        "id": "813d116e-ecdc-4d86-bc38-87ad43b92d51",
        "name": "Recipe 29",
        "description": "A generic description",
        "image": "https://source.unsplash.com/random",
        "average_time": "4883",
        "average_rate": "6",
        "ingredients": [
            "e848b471-f922-4d23-a427-668c47ce1629",
            "5f073432-628d-40cd-b10e-e2d16b7cc6c4",
            "6ef34979-9123-4c30-8804-3b863c64c113",
            "8287e154-daa4-444d-8eca-4d4155c724b2",
            "b3f13f2f-d2d4-4e15-8e06-5c9f822ec712"
        ],
        "steps": [
            {
                "name": "Step 1",
                "description": "A generic description"
            },
            {
                "name": "Step 2",
                "description": "A generic description"
            },
            {
                "name": "Step 3",
                "description": "A generic description"
            },
            {
                "name": "Step 4",
                "description": "A generic description"
            }
        ]
    },
    {
        "id": "0927ad87-a17d-4e16-95d0-cb11bc33bfe7",
        "name": "Recipe 30",
        "description": "A generic description",
        "image": "https://source.unsplash.com/random",
        "average_time": "4200",
        "average_rate": "1",
        "ingredients": [
            "8287e154-daa4-444d-8eca-4d4155c724b2",
            "b3f13f2f-d2d4-4e15-8e06-5c9f822ec712",
            "3034ee5d-7072-4e40-8cbb-ed8aa4d6f1df",
            "5f073432-628d-40cd-b10e-e2d16b7cc6c4",
            "e848b471-f922-4d23-a427-668c47ce1629"
        ],
        "steps": [
            {
                "name": "Step 1",
                "description": "A generic description"
            },
            {
                "name": "Step 2",
                "description": "A generic description"
            }
        ]
    },
    {
        "id": "417be32f-585f-40b5-bfc4-a4b78069347f",
        "name": "Recipe 31",
        "description": "A generic description",
        "image": "https://source.unsplash.com/random",
        "average_time": "1162",
        "average_rate": "6",
        "ingredients": [
            "5f073432-628d-40cd-b10e-e2d16b7cc6c4",
            "b3f13f2f-d2d4-4e15-8e06-5c9f822ec712",
            "6ef34979-9123-4c30-8804-3b863c64c113",
            "3034ee5d-7072-4e40-8cbb-ed8aa4d6f1df",
            "8287e154-daa4-444d-8eca-4d4155c724b2",
            "e848b471-f922-4d23-a427-668c47ce1629"
        ],
        "steps": [
            {
                "name": "Step 1",
                "description": "A generic description"
            },
            {
                "name": "Step 2",
                "description": "A generic description"
            },
            {
                "name": "Step 3",
                "description": "A generic description"
            },
            {
                "name": "Step 4",
                "description": "A generic description"
            },
            {
                "name": "Step 5",
                "description": "A generic description"
            },
            {
                "name": "Step 6",
                "description": "A generic description"
            },
            {
                "name": "Step 7",
                "description": "A generic description"
            }
        ]
    },
    {
        "id": "c6bbc0c1-9952-4ab2-9891-9186921db441",
        "name": "Recipe 32",
        "description": "A generic description",
        "image": "https://source.unsplash.com/random",
        "average_time": "567",
        "average_rate": "5",
        "ingredients": [
            "8287e154-daa4-444d-8eca-4d4155c724b2",
            "5f073432-628d-40cd-b10e-e2d16b7cc6c4",
            "b3f13f2f-d2d4-4e15-8e06-5c9f822ec712",
            "6ef34979-9123-4c30-8804-3b863c64c113",
            "e848b471-f922-4d23-a427-668c47ce1629"
        ],
        "steps": [
            {
                "name": "Step 1",
                "description": "A generic description"
            },
            {
                "name": "Step 2",
                "description": "A generic description"
            },
            {
                "name": "Step 3",
                "description": "A generic description"
            },
            {
                "name": "Step 4",
                "description": "A generic description"
            },
            {
                "name": "Step 5",
                "description": "A generic description"
            }
        ]
    },
    {
        "id": "f6295908-f8b4-4da6-b396-744e4b2c5e62",
        "name": "Recipe 33",
        "description": "A generic description",
        "image": "https://source.unsplash.com/random",
        "average_time": "977",
        "average_rate": "4",
        "ingredients": [
            "6ef34979-9123-4c30-8804-3b863c64c113",
            "5f073432-628d-40cd-b10e-e2d16b7cc6c4",
            "e848b471-f922-4d23-a427-668c47ce1629",
            "8287e154-daa4-444d-8eca-4d4155c724b2",
            "b3f13f2f-d2d4-4e15-8e06-5c9f822ec712"
        ],
        "steps": [
            {
                "name": "Step 1",
                "description": "A generic description"
            },
            {
                "name": "Step 2",
                "description": "A generic description"
            },
            {
                "name": "Step 3",
                "description": "A generic description"
            },
            {
                "name": "Step 4",
                "description": "A generic description"
            },
            {
                "name": "Step 5",
                "description": "A generic description"
            },
            {
                "name": "Step 6",
                "description": "A generic description"
            }
        ]
    },
    {
        "id": "21983a9f-42c2-4bf4-9c67-2e6deb3670c3",
        "name": "Recipe 34",
        "description": "A generic description",
        "image": "https://source.unsplash.com/random",
        "average_time": "4365",
        "average_rate": "1",
        "ingredients": [
            "b3f13f2f-d2d4-4e15-8e06-5c9f822ec712",
            "5f073432-628d-40cd-b10e-e2d16b7cc6c4",
            "8287e154-daa4-444d-8eca-4d4155c724b2",
            "3034ee5d-7072-4e40-8cbb-ed8aa4d6f1df",
            "e848b471-f922-4d23-a427-668c47ce1629",
            "6ef34979-9123-4c30-8804-3b863c64c113"
        ],
        "steps": [
            {
                "name": "Step 1",
                "description": "A generic description"
            },
            {
                "name": "Step 2",
                "description": "A generic description"
            },
            {
                "name": "Step 3",
                "description": "A generic description"
            },
            {
                "name": "Step 4",
                "description": "A generic description"
            },
            {
                "name": "Step 5",
                "description": "A generic description"
            }
        ]
    },
    {
        "id": "1e965c2f-2913-4776-8f9d-07c1b1c81896",
        "name": "Recipe 35",
        "description": "A generic description",
        "image": "https://source.unsplash.com/random",
        "average_time": "1495",
        "average_rate": "1",
        "ingredients": [
            "8287e154-daa4-444d-8eca-4d4155c724b2",
            "e848b471-f922-4d23-a427-668c47ce1629",
            "6ef34979-9123-4c30-8804-3b863c64c113",
            "3034ee5d-7072-4e40-8cbb-ed8aa4d6f1df",
            "5f073432-628d-40cd-b10e-e2d16b7cc6c4",
            "b3f13f2f-d2d4-4e15-8e06-5c9f822ec712"
        ],
        "steps": [
            {
                "name": "Step 1",
                "description": "A generic description"
            },
            {
                "name": "Step 2",
                "description": "A generic description"
            },
            {
                "name": "Step 3",
                "description": "A generic description"
            },
            {
                "name": "Step 4",
                "description": "A generic description"
            }
        ]
    },
    {
        "id": "202075f3-af01-49f6-bd6e-07aa924c8e39",
        "name": "Recipe 36",
        "description": "A generic description",
        "image": "https://source.unsplash.com/random",
        "average_time": "2081",
        "average_rate": "5",
        "ingredients": [
            "8287e154-daa4-444d-8eca-4d4155c724b2",
            "e848b471-f922-4d23-a427-668c47ce1629",
            "5f073432-628d-40cd-b10e-e2d16b7cc6c4",
            "6ef34979-9123-4c30-8804-3b863c64c113"
        ],
        "steps": [
            {
                "name": "Step 1",
                "description": "A generic description"
            },
            {
                "name": "Step 2",
                "description": "A generic description"
            },
            {
                "name": "Step 3",
                "description": "A generic description"
            },
            {
                "name": "Step 4",
                "description": "A generic description"
            },
            {
                "name": "Step 5",
                "description": "A generic description"
            },
            {
                "name": "Step 6",
                "description": "A generic description"
            },
            {
                "name": "Step 7",
                "description": "A generic description"
            },
            {
                "name": "Step 8",
                "description": "A generic description"
            }
        ]
    },
    {
        "id": "1d26d83e-9305-48a5-b00f-5aec8cf6c510",
        "name": "Recipe 37",
        "description": "A generic description",
        "image": "https://source.unsplash.com/random",
        "average_time": "1978",
        "average_rate": "3",
        "ingredients": [
            "8287e154-daa4-444d-8eca-4d4155c724b2",
            "3034ee5d-7072-4e40-8cbb-ed8aa4d6f1df",
            "b3f13f2f-d2d4-4e15-8e06-5c9f822ec712",
            "5f073432-628d-40cd-b10e-e2d16b7cc6c4",
            "e848b471-f922-4d23-a427-668c47ce1629",
            "6ef34979-9123-4c30-8804-3b863c64c113"
        ],
        "steps": [
            {
                "name": "Step 1",
                "description": "A generic description"
            },
            {
                "name": "Step 2",
                "description": "A generic description"
            },
            {
                "name": "Step 3",
                "description": "A generic description"
            }
        ]
    },
    {
        "id": "d124b014-dc3e-4966-aa9d-bc0cc0b60344",
        "name": "Recipe 38",
        "description": "A generic description",
        "image": "https://source.unsplash.com/random",
        "average_time": "967",
        "average_rate": "4",
        "ingredients": [
            "b3f13f2f-d2d4-4e15-8e06-5c9f822ec712",
            "6ef34979-9123-4c30-8804-3b863c64c113",
            "3034ee5d-7072-4e40-8cbb-ed8aa4d6f1df",
            "e848b471-f922-4d23-a427-668c47ce1629",
            "5f073432-628d-40cd-b10e-e2d16b7cc6c4"
        ],
        "steps": [
            {
                "name": "Step 1",
                "description": "A generic description"
            },
            {
                "name": "Step 2",
                "description": "A generic description"
            },
            {
                "name": "Step 3",
                "description": "A generic description"
            }
        ]
    },
    {
        "id": "1a3f15a8-db53-43f8-887a-7466f97ba1dc",
        "name": "Recipe 39",
        "description": "A generic description",
        "image": "https://source.unsplash.com/random",
        "average_time": "1163",
        "average_rate": "2",
        "ingredients": [
            "6ef34979-9123-4c30-8804-3b863c64c113",
            "5f073432-628d-40cd-b10e-e2d16b7cc6c4",
            "b3f13f2f-d2d4-4e15-8e06-5c9f822ec712"
        ],
        "steps": [
            {
                "name": "Step 1",
                "description": "A generic description"
            },
            {
                "name": "Step 2",
                "description": "A generic description"
            },
            {
                "name": "Step 3",
                "description": "A generic description"
            }
        ]
    },
    {
        "id": "a7fcdb3f-a520-4be8-a001-d156e195131a",
        "name": "Recipe 40",
        "description": "A generic description",
        "image": "https://source.unsplash.com/random",
        "average_time": "4480",
        "average_rate": "3",
        "ingredients": [
            "6ef34979-9123-4c30-8804-3b863c64c113",
            "8287e154-daa4-444d-8eca-4d4155c724b2",
            "e848b471-f922-4d23-a427-668c47ce1629",
            "5f073432-628d-40cd-b10e-e2d16b7cc6c4",
            "b3f13f2f-d2d4-4e15-8e06-5c9f822ec712"
        ],
        "steps": [
            {
                "name": "Step 1",
                "description": "A generic description"
            },
            {
                "name": "Step 2",
                "description": "A generic description"
            },
            {
                "name": "Step 3",
                "description": "A generic description"
            },
            {
                "name": "Step 4",
                "description": "A generic description"
            },
            {
                "name": "Step 5",
                "description": "A generic description"
            },
            {
                "name": "Step 6",
                "description": "A generic description"
            },
            {
                "name": "Step 7",
                "description": "A generic description"
            }
        ]
    },
    {
        "id": "fdbad957-69a9-4ddc-aae0-f96935711601",
        "name": "Recipe 41",
        "description": "A generic description",
        "image": "https://source.unsplash.com/random",
        "average_time": "3087",
        "average_rate": "6",
        "ingredients": [
            "5f073432-628d-40cd-b10e-e2d16b7cc6c4",
            "b3f13f2f-d2d4-4e15-8e06-5c9f822ec712",
            "6ef34979-9123-4c30-8804-3b863c64c113",
            "8287e154-daa4-444d-8eca-4d4155c724b2",
            "3034ee5d-7072-4e40-8cbb-ed8aa4d6f1df",
            "e848b471-f922-4d23-a427-668c47ce1629"
        ],
        "steps": [
            {
                "name": "Step 1",
                "description": "A generic description"
            },
            {
                "name": "Step 2",
                "description": "A generic description"
            },
            {
                "name": "Step 3",
                "description": "A generic description"
            },
            {
                "name": "Step 4",
                "description": "A generic description"
            },
            {
                "name": "Step 5",
                "description": "A generic description"
            }
        ]
    },
    {
        "id": "1af002aa-a6d5-4d34-97a7-dd247b360f5c",
        "name": "Recipe 42",
        "description": "A generic description",
        "image": "https://source.unsplash.com/random",
        "average_time": "3872",
        "average_rate": "5",
        "ingredients": [
            "5f073432-628d-40cd-b10e-e2d16b7cc6c4",
            "8287e154-daa4-444d-8eca-4d4155c724b2",
            "b3f13f2f-d2d4-4e15-8e06-5c9f822ec712",
            "6ef34979-9123-4c30-8804-3b863c64c113"
        ],
        "steps": [
            {
                "name": "Step 1",
                "description": "A generic description"
            },
            {
                "name": "Step 2",
                "description": "A generic description"
            }
        ]
    },
    {
        "id": "ff7b39a5-d3e7-4826-8437-deace7ce17e5",
        "name": "Recipe 43",
        "description": "A generic description",
        "image": "https://source.unsplash.com/random",
        "average_time": "4705",
        "average_rate": "0",
        "ingredients": [
            "e848b471-f922-4d23-a427-668c47ce1629",
            "3034ee5d-7072-4e40-8cbb-ed8aa4d6f1df",
            "8287e154-daa4-444d-8eca-4d4155c724b2",
            "6ef34979-9123-4c30-8804-3b863c64c113"
        ],
        "steps": [
            {
                "name": "Step 1",
                "description": "A generic description"
            },
            {
                "name": "Step 2",
                "description": "A generic description"
            },
            {
                "name": "Step 3",
                "description": "A generic description"
            },
            {
                "name": "Step 4",
                "description": "A generic description"
            },
            {
                "name": "Step 5",
                "description": "A generic description"
            },
            {
                "name": "Step 6",
                "description": "A generic description"
            },
            {
                "name": "Step 7",
                "description": "A generic description"
            },
            {
                "name": "Step 8",
                "description": "A generic description"
            },
            {
                "name": "Step 9",
                "description": "A generic description"
            },
            {
                "name": "Step 10",
                "description": "A generic description"
            }
        ]
    },
    {
        "id": "315ac58e-dbed-4782-a6b9-5b5ffa8b742e",
        "name": "Recipe 44",
        "description": "A generic description",
        "image": "https://source.unsplash.com/random",
        "average_time": "1238",
        "average_rate": "2",
        "ingredients": [
            "b3f13f2f-d2d4-4e15-8e06-5c9f822ec712",
            "e848b471-f922-4d23-a427-668c47ce1629",
            "8287e154-daa4-444d-8eca-4d4155c724b2",
            "5f073432-628d-40cd-b10e-e2d16b7cc6c4",
            "6ef34979-9123-4c30-8804-3b863c64c113",
            "3034ee5d-7072-4e40-8cbb-ed8aa4d6f1df"
        ],
        "steps": [
            {
                "name": "Step 1",
                "description": "A generic description"
            },
            {
                "name": "Step 2",
                "description": "A generic description"
            },
            {
                "name": "Step 3",
                "description": "A generic description"
            },
            {
                "name": "Step 4",
                "description": "A generic description"
            },
            {
                "name": "Step 5",
                "description": "A generic description"
            },
            {
                "name": "Step 6",
                "description": "A generic description"
            },
            {
                "name": "Step 7",
                "description": "A generic description"
            },
            {
                "name": "Step 8",
                "description": "A generic description"
            },
            {
                "name": "Step 9",
                "description": "A generic description"
            }
        ]
    },
    {
        "id": "1782e784-0248-4ba7-a616-fa224b67136a",
        "name": "Recipe 45",
        "description": "A generic description",
        "image": "https://source.unsplash.com/random",
        "average_time": "3529",
        "average_rate": "4",
        "ingredients": [
            "5f073432-628d-40cd-b10e-e2d16b7cc6c4",
            "8287e154-daa4-444d-8eca-4d4155c724b2",
            "6ef34979-9123-4c30-8804-3b863c64c113",
            "b3f13f2f-d2d4-4e15-8e06-5c9f822ec712"
        ],
        "steps": [
            {
                "name": "Step 1",
                "description": "A generic description"
            },
            {
                "name": "Step 2",
                "description": "A generic description"
            },
            {
                "name": "Step 3",
                "description": "A generic description"
            },
            {
                "name": "Step 4",
                "description": "A generic description"
            },
            {
                "name": "Step 5",
                "description": "A generic description"
            },
            {
                "name": "Step 6",
                "description": "A generic description"
            },
            {
                "name": "Step 7",
                "description": "A generic description"
            },
            {
                "name": "Step 8",
                "description": "A generic description"
            }
        ]
    },
    {
        "id": "19271aaf-c7b0-44cf-89b5-214779839778",
        "name": "Recipe 46",
        "description": "A generic description",
        "image": "https://source.unsplash.com/random",
        "average_time": "4305",
        "average_rate": "3",
        "ingredients": [
            "5f073432-628d-40cd-b10e-e2d16b7cc6c4",
            "6ef34979-9123-4c30-8804-3b863c64c113",
            "8287e154-daa4-444d-8eca-4d4155c724b2",
            "e848b471-f922-4d23-a427-668c47ce1629",
            "b3f13f2f-d2d4-4e15-8e06-5c9f822ec712",
            "3034ee5d-7072-4e40-8cbb-ed8aa4d6f1df"
        ],
        "steps": [
            {
                "name": "Step 1",
                "description": "A generic description"
            },
            {
                "name": "Step 2",
                "description": "A generic description"
            },
            {
                "name": "Step 3",
                "description": "A generic description"
            },
            {
                "name": "Step 4",
                "description": "A generic description"
            },
            {
                "name": "Step 5",
                "description": "A generic description"
            },
            {
                "name": "Step 6",
                "description": "A generic description"
            },
            {
                "name": "Step 7",
                "description": "A generic description"
            },
            {
                "name": "Step 8",
                "description": "A generic description"
            }
        ]
    },
    {
        "id": "d9a57af4-40be-4465-b0ef-69a9cdf17a77",
        "name": "Recipe 47",
        "description": "A generic description",
        "image": "https://source.unsplash.com/random",
        "average_time": "1425",
        "average_rate": "6",
        "ingredients": [
            "8287e154-daa4-444d-8eca-4d4155c724b2",
            "6ef34979-9123-4c30-8804-3b863c64c113",
            "e848b471-f922-4d23-a427-668c47ce1629",
            "3034ee5d-7072-4e40-8cbb-ed8aa4d6f1df"
        ],
        "steps": [
            {
                "name": "Step 1",
                "description": "A generic description"
            },
            {
                "name": "Step 2",
                "description": "A generic description"
            }
        ]
    },
    {
        "id": "5484ffee-20d0-43b1-a9a2-b2255b82ac20",
        "name": "Recipe 48",
        "description": "A generic description",
        "image": "https://source.unsplash.com/random",
        "average_time": "2143",
        "average_rate": "1",
        "ingredients": [
            "6ef34979-9123-4c30-8804-3b863c64c113",
            "e848b471-f922-4d23-a427-668c47ce1629",
            "b3f13f2f-d2d4-4e15-8e06-5c9f822ec712",
            "5f073432-628d-40cd-b10e-e2d16b7cc6c4",
            "8287e154-daa4-444d-8eca-4d4155c724b2"
        ],
        "steps": [
            {
                "name": "Step 1",
                "description": "A generic description"
            },
            {
                "name": "Step 2",
                "description": "A generic description"
            },
            {
                "name": "Step 3",
                "description": "A generic description"
            }
        ]
    },
    {
        "id": "2a7d9717-6393-4d44-94a0-f1aafc746541",
        "name": "Recipe 49",
        "description": "A generic description",
        "image": "https://source.unsplash.com/random",
        "average_time": "1110",
        "average_rate": "6",
        "ingredients": [
            "3034ee5d-7072-4e40-8cbb-ed8aa4d6f1df",
            "8287e154-daa4-444d-8eca-4d4155c724b2",
            "e848b471-f922-4d23-a427-668c47ce1629",
            "5f073432-628d-40cd-b10e-e2d16b7cc6c4",
            "b3f13f2f-d2d4-4e15-8e06-5c9f822ec712",
            "6ef34979-9123-4c30-8804-3b863c64c113"
        ],
        "steps": [
            {
                "name": "Step 1",
                "description": "A generic description"
            },
            {
                "name": "Step 2",
                "description": "A generic description"
            },
            {
                "name": "Step 3",
                "description": "A generic description"
            },
            {
                "name": "Step 4",
                "description": "A generic description"
            },
            {
                "name": "Step 5",
                "description": "A generic description"
            }
        ]
    },
    {
        "id": "cf63fb5f-cfc3-49c2-9534-111d0b875460",
        "name": "Recipe 50",
        "description": "A generic description",
        "image": "https://source.unsplash.com/random",
        "average_time": "1806",
        "average_rate": "2",
        "ingredients": [
            "e848b471-f922-4d23-a427-668c47ce1629",
            "3034ee5d-7072-4e40-8cbb-ed8aa4d6f1df"
        ],
        "steps": [
            {
                "name": "Step 1",
                "description": "A generic description"
            },
            {
                "name": "Step 2",
                "description": "A generic description"
            },
            {
                "name": "Step 3",
                "description": "A generic description"
            }
        ]
    },
    {
        "id": "d9b4c931-dfe0-4076-ba46-b4e61579db5f",
        "name": "Recipe 51",
        "description": "A generic description",
        "image": "https://source.unsplash.com/random",
        "average_time": "1618",
        "average_rate": "5",
        "ingredients": [
            "3034ee5d-7072-4e40-8cbb-ed8aa4d6f1df",
            "b3f13f2f-d2d4-4e15-8e06-5c9f822ec712",
            "e848b471-f922-4d23-a427-668c47ce1629",
            "5f073432-628d-40cd-b10e-e2d16b7cc6c4",
            "6ef34979-9123-4c30-8804-3b863c64c113",
            "8287e154-daa4-444d-8eca-4d4155c724b2"
        ],
        "steps": [
            {
                "name": "Step 1",
                "description": "A generic description"
            },
            {
                "name": "Step 2",
                "description": "A generic description"
            },
            {
                "name": "Step 3",
                "description": "A generic description"
            },
            {
                "name": "Step 4",
                "description": "A generic description"
            },
            {
                "name": "Step 5",
                "description": "A generic description"
            },
            {
                "name": "Step 6",
                "description": "A generic description"
            },
            {
                "name": "Step 7",
                "description": "A generic description"
            },
            {
                "name": "Step 8",
                "description": "A generic description"
            }
        ]
    },
    {
        "id": "3559ac71-9040-4e00-bc52-24ab2d8a61c8",
        "name": "Recipe 52",
        "description": "A generic description",
        "image": "https://source.unsplash.com/random",
        "average_time": "4826",
        "average_rate": "5",
        "ingredients": [
            "6ef34979-9123-4c30-8804-3b863c64c113",
            "8287e154-daa4-444d-8eca-4d4155c724b2",
            "3034ee5d-7072-4e40-8cbb-ed8aa4d6f1df",
            "b3f13f2f-d2d4-4e15-8e06-5c9f822ec712",
            "e848b471-f922-4d23-a427-668c47ce1629"
        ],
        "steps": [
            {
                "name": "Step 1",
                "description": "A generic description"
            },
            {
                "name": "Step 2",
                "description": "A generic description"
            },
            {
                "name": "Step 3",
                "description": "A generic description"
            },
            {
                "name": "Step 4",
                "description": "A generic description"
            },
            {
                "name": "Step 5",
                "description": "A generic description"
            },
            {
                "name": "Step 6",
                "description": "A generic description"
            }
        ]
    },
    {
        "id": "f682d569-53d1-4eab-bc61-591729a270dc",
        "name": "Recipe 53",
        "description": "A generic description",
        "image": "https://source.unsplash.com/random",
        "average_time": "905",
        "average_rate": "5",
        "ingredients": [
            "b3f13f2f-d2d4-4e15-8e06-5c9f822ec712",
            "8287e154-daa4-444d-8eca-4d4155c724b2",
            "5f073432-628d-40cd-b10e-e2d16b7cc6c4",
            "6ef34979-9123-4c30-8804-3b863c64c113",
            "3034ee5d-7072-4e40-8cbb-ed8aa4d6f1df"
        ],
        "steps": [
            {
                "name": "Step 1",
                "description": "A generic description"
            },
            {
                "name": "Step 2",
                "description": "A generic description"
            },
            {
                "name": "Step 3",
                "description": "A generic description"
            },
            {
                "name": "Step 4",
                "description": "A generic description"
            },
            {
                "name": "Step 5",
                "description": "A generic description"
            },
            {
                "name": "Step 6",
                "description": "A generic description"
            },
            {
                "name": "Step 7",
                "description": "A generic description"
            }
        ]
    },
    {
        "id": "276a11fc-1b86-40d6-a0ce-9dd59c9895ce",
        "name": "Recipe 54",
        "description": "A generic description",
        "image": "https://source.unsplash.com/random",
        "average_time": "1867",
        "average_rate": "4",
        "ingredients": [
            "e848b471-f922-4d23-a427-668c47ce1629",
            "5f073432-628d-40cd-b10e-e2d16b7cc6c4",
            "3034ee5d-7072-4e40-8cbb-ed8aa4d6f1df",
            "8287e154-daa4-444d-8eca-4d4155c724b2"
        ],
        "steps": [
            {
                "name": "Step 1",
                "description": "A generic description"
            },
            {
                "name": "Step 2",
                "description": "A generic description"
            },
            {
                "name": "Step 3",
                "description": "A generic description"
            },
            {
                "name": "Step 4",
                "description": "A generic description"
            }
        ]
    },
    {
        "id": "dbfc3a4d-6f68-451b-b7ad-615d8d196259",
        "name": "Recipe 55",
        "description": "A generic description",
        "image": "https://source.unsplash.com/random",
        "average_time": "323",
        "average_rate": "4",
        "ingredients": [
            "6ef34979-9123-4c30-8804-3b863c64c113",
            "b3f13f2f-d2d4-4e15-8e06-5c9f822ec712",
            "e848b471-f922-4d23-a427-668c47ce1629",
            "8287e154-daa4-444d-8eca-4d4155c724b2",
            "5f073432-628d-40cd-b10e-e2d16b7cc6c4"
        ],
        "steps": [
            {
                "name": "Step 1",
                "description": "A generic description"
            },
            {
                "name": "Step 2",
                "description": "A generic description"
            },
            {
                "name": "Step 3",
                "description": "A generic description"
            },
            {
                "name": "Step 4",
                "description": "A generic description"
            },
            {
                "name": "Step 5",
                "description": "A generic description"
            },
            {
                "name": "Step 6",
                "description": "A generic description"
            },
            {
                "name": "Step 7",
                "description": "A generic description"
            },
            {
                "name": "Step 8",
                "description": "A generic description"
            },
            {
                "name": "Step 9",
                "description": "A generic description"
            },
            {
                "name": "Step 10",
                "description": "A generic description"
            }
        ]
    },
    {
        "id": "a309be41-0ca9-410a-9139-cc99a7f22fc6",
        "name": "Recipe 56",
        "description": "A generic description",
        "image": "https://source.unsplash.com/random",
        "average_time": "1464",
        "average_rate": "0",
        "ingredients": [
            "e848b471-f922-4d23-a427-668c47ce1629",
            "b3f13f2f-d2d4-4e15-8e06-5c9f822ec712",
            "5f073432-628d-40cd-b10e-e2d16b7cc6c4",
            "6ef34979-9123-4c30-8804-3b863c64c113",
            "8287e154-daa4-444d-8eca-4d4155c724b2",
            "3034ee5d-7072-4e40-8cbb-ed8aa4d6f1df"
        ],
        "steps": [
            {
                "name": "Step 1",
                "description": "A generic description"
            },
            {
                "name": "Step 2",
                "description": "A generic description"
            },
            {
                "name": "Step 3",
                "description": "A generic description"
            },
            {
                "name": "Step 4",
                "description": "A generic description"
            },
            {
                "name": "Step 5",
                "description": "A generic description"
            },
            {
                "name": "Step 6",
                "description": "A generic description"
            },
            {
                "name": "Step 7",
                "description": "A generic description"
            },
            {
                "name": "Step 8",
                "description": "A generic description"
            },
            {
                "name": "Step 9",
                "description": "A generic description"
            },
            {
                "name": "Step 10",
                "description": "A generic description"
            }
        ]
    },
    {
        "id": "39b6ab33-fada-4115-8532-e75f21e97125",
        "name": "Recipe 57",
        "description": "A generic description",
        "image": "https://source.unsplash.com/random",
        "average_time": "2402",
        "average_rate": "1",
        "ingredients": [
            "5f073432-628d-40cd-b10e-e2d16b7cc6c4",
            "e848b471-f922-4d23-a427-668c47ce1629",
            "b3f13f2f-d2d4-4e15-8e06-5c9f822ec712",
            "6ef34979-9123-4c30-8804-3b863c64c113"
        ],
        "steps": [
            {
                "name": "Step 1",
                "description": "A generic description"
            },
            {
                "name": "Step 2",
                "description": "A generic description"
            },
            {
                "name": "Step 3",
                "description": "A generic description"
            },
            {
                "name": "Step 4",
                "description": "A generic description"
            },
            {
                "name": "Step 5",
                "description": "A generic description"
            },
            {
                "name": "Step 6",
                "description": "A generic description"
            },
            {
                "name": "Step 7",
                "description": "A generic description"
            },
            {
                "name": "Step 8",
                "description": "A generic description"
            },
            {
                "name": "Step 9",
                "description": "A generic description"
            },
            {
                "name": "Step 10",
                "description": "A generic description"
            }
        ]
    },
    {
        "id": "7164af08-def7-4f11-a28b-ae897be31501",
        "name": "Recipe 58",
        "description": "A generic description",
        "image": "https://source.unsplash.com/random",
        "average_time": "3346",
        "average_rate": "3",
        "ingredients": [
            "5f073432-628d-40cd-b10e-e2d16b7cc6c4",
            "b3f13f2f-d2d4-4e15-8e06-5c9f822ec712",
            "8287e154-daa4-444d-8eca-4d4155c724b2",
            "6ef34979-9123-4c30-8804-3b863c64c113",
            "3034ee5d-7072-4e40-8cbb-ed8aa4d6f1df",
            "e848b471-f922-4d23-a427-668c47ce1629"
        ],
        "steps": [
            {
                "name": "Step 1",
                "description": "A generic description"
            },
            {
                "name": "Step 2",
                "description": "A generic description"
            },
            {
                "name": "Step 3",
                "description": "A generic description"
            },
            {
                "name": "Step 4",
                "description": "A generic description"
            }
        ]
    },
    {
        "id": "7898b808-d2eb-40ff-be7e-1ef69ffb72b5",
        "name": "Recipe 59",
        "description": "A generic description",
        "image": "https://source.unsplash.com/random",
        "average_time": "3419",
        "average_rate": "2",
        "ingredients": [
            "6ef34979-9123-4c30-8804-3b863c64c113",
            "5f073432-628d-40cd-b10e-e2d16b7cc6c4",
            "8287e154-daa4-444d-8eca-4d4155c724b2",
            "3034ee5d-7072-4e40-8cbb-ed8aa4d6f1df",
            "e848b471-f922-4d23-a427-668c47ce1629",
            "b3f13f2f-d2d4-4e15-8e06-5c9f822ec712"
        ],
        "steps": [
            {
                "name": "Step 1",
                "description": "A generic description"
            },
            {
                "name": "Step 2",
                "description": "A generic description"
            },
            {
                "name": "Step 3",
                "description": "A generic description"
            },
            {
                "name": "Step 4",
                "description": "A generic description"
            },
            {
                "name": "Step 5",
                "description": "A generic description"
            },
            {
                "name": "Step 6",
                "description": "A generic description"
            },
            {
                "name": "Step 7",
                "description": "A generic description"
            },
            {
                "name": "Step 8",
                "description": "A generic description"
            },
            {
                "name": "Step 9",
                "description": "A generic description"
            },
            {
                "name": "Step 10",
                "description": "A generic description"
            }
        ]
    },
    {
        "id": "db20e812-ef9b-494b-a5c1-6270bbd417df",
        "name": "Recipe 60",
        "description": "A generic description",
        "image": "https://source.unsplash.com/random",
        "average_time": "2963",
        "average_rate": "4",
        "ingredients": [
            "6ef34979-9123-4c30-8804-3b863c64c113",
            "8287e154-daa4-444d-8eca-4d4155c724b2",
            "e848b471-f922-4d23-a427-668c47ce1629",
            "5f073432-628d-40cd-b10e-e2d16b7cc6c4",
            "b3f13f2f-d2d4-4e15-8e06-5c9f822ec712",
            "3034ee5d-7072-4e40-8cbb-ed8aa4d6f1df"
        ],
        "steps": [
            {
                "name": "Step 1",
                "description": "A generic description"
            },
            {
                "name": "Step 2",
                "description": "A generic description"
            },
            {
                "name": "Step 3",
                "description": "A generic description"
            },
            {
                "name": "Step 4",
                "description": "A generic description"
            },
            {
                "name": "Step 5",
                "description": "A generic description"
            }
        ]
    },
    {
        "id": "651d8830-8940-4ace-862b-536500fc8f95",
        "name": "Recipe 61",
        "description": "A generic description",
        "image": "https://source.unsplash.com/random",
        "average_time": "625",
        "average_rate": "2",
        "ingredients": [
            "3034ee5d-7072-4e40-8cbb-ed8aa4d6f1df",
            "b3f13f2f-d2d4-4e15-8e06-5c9f822ec712",
            "8287e154-daa4-444d-8eca-4d4155c724b2",
            "5f073432-628d-40cd-b10e-e2d16b7cc6c4",
            "e848b471-f922-4d23-a427-668c47ce1629"
        ],
        "steps": [
            {
                "name": "Step 1",
                "description": "A generic description"
            },
            {
                "name": "Step 2",
                "description": "A generic description"
            },
            {
                "name": "Step 3",
                "description": "A generic description"
            },
            {
                "name": "Step 4",
                "description": "A generic description"
            },
            {
                "name": "Step 5",
                "description": "A generic description"
            },
            {
                "name": "Step 6",
                "description": "A generic description"
            },
            {
                "name": "Step 7",
                "description": "A generic description"
            },
            {
                "name": "Step 8",
                "description": "A generic description"
            },
            {
                "name": "Step 9",
                "description": "A generic description"
            },
            {
                "name": "Step 10",
                "description": "A generic description"
            }
        ]
    },
    {
        "id": "59f43280-8fda-468e-9210-c11f7d10a752",
        "name": "Recipe 62",
        "description": "A generic description",
        "image": "https://source.unsplash.com/random",
        "average_time": "1639",
        "average_rate": "0",
        "ingredients": [
            "5f073432-628d-40cd-b10e-e2d16b7cc6c4",
            "e848b471-f922-4d23-a427-668c47ce1629",
            "3034ee5d-7072-4e40-8cbb-ed8aa4d6f1df",
            "6ef34979-9123-4c30-8804-3b863c64c113",
            "b3f13f2f-d2d4-4e15-8e06-5c9f822ec712"
        ],
        "steps": [
            {
                "name": "Step 1",
                "description": "A generic description"
            },
            {
                "name": "Step 2",
                "description": "A generic description"
            },
            {
                "name": "Step 3",
                "description": "A generic description"
            },
            {
                "name": "Step 4",
                "description": "A generic description"
            },
            {
                "name": "Step 5",
                "description": "A generic description"
            },
            {
                "name": "Step 6",
                "description": "A generic description"
            },
            {
                "name": "Step 7",
                "description": "A generic description"
            }
        ]
    },
    {
        "id": "3216a2b9-00e4-443e-8c2a-9173b4d40fc3",
        "name": "Recipe 63",
        "description": "A generic description",
        "image": "https://source.unsplash.com/random",
        "average_time": "3002",
        "average_rate": "4",
        "ingredients": [
            "e848b471-f922-4d23-a427-668c47ce1629",
            "5f073432-628d-40cd-b10e-e2d16b7cc6c4",
            "8287e154-daa4-444d-8eca-4d4155c724b2"
        ],
        "steps": [
            {
                "name": "Step 1",
                "description": "A generic description"
            },
            {
                "name": "Step 2",
                "description": "A generic description"
            }
        ]
    },
    {
        "id": "98ecfe87-aa33-47ac-8934-72711d8bd1db",
        "name": "Recipe 64",
        "description": "A generic description",
        "image": "https://source.unsplash.com/random",
        "average_time": "3472",
        "average_rate": "0",
        "ingredients": [
            "b3f13f2f-d2d4-4e15-8e06-5c9f822ec712",
            "e848b471-f922-4d23-a427-668c47ce1629",
            "3034ee5d-7072-4e40-8cbb-ed8aa4d6f1df"
        ],
        "steps": [
            {
                "name": "Step 1",
                "description": "A generic description"
            },
            {
                "name": "Step 2",
                "description": "A generic description"
            },
            {
                "name": "Step 3",
                "description": "A generic description"
            },
            {
                "name": "Step 4",
                "description": "A generic description"
            },
            {
                "name": "Step 5",
                "description": "A generic description"
            },
            {
                "name": "Step 6",
                "description": "A generic description"
            },
            {
                "name": "Step 7",
                "description": "A generic description"
            },
            {
                "name": "Step 8",
                "description": "A generic description"
            },
            {
                "name": "Step 9",
                "description": "A generic description"
            },
            {
                "name": "Step 10",
                "description": "A generic description"
            }
        ]
    },
    {
        "id": "31fc0e98-12a1-4f25-8fb6-c4f29f4e2c21",
        "name": "Recipe 65",
        "description": "A generic description",
        "image": "https://source.unsplash.com/random",
        "average_time": "4643",
        "average_rate": "2",
        "ingredients": [
            "6ef34979-9123-4c30-8804-3b863c64c113",
            "e848b471-f922-4d23-a427-668c47ce1629"
        ],
        "steps": [
            {
                "name": "Step 1",
                "description": "A generic description"
            },
            {
                "name": "Step 2",
                "description": "A generic description"
            },
            {
                "name": "Step 3",
                "description": "A generic description"
            },
            {
                "name": "Step 4",
                "description": "A generic description"
            },
            {
                "name": "Step 5",
                "description": "A generic description"
            }
        ]
    },
    {
        "id": "270c7f93-cf47-461f-8727-ba12e2dad31f",
        "name": "Recipe 66",
        "description": "A generic description",
        "image": "https://source.unsplash.com/random",
        "average_time": "3296",
        "average_rate": "6",
        "ingredients": [
            "8287e154-daa4-444d-8eca-4d4155c724b2",
            "5f073432-628d-40cd-b10e-e2d16b7cc6c4",
            "3034ee5d-7072-4e40-8cbb-ed8aa4d6f1df",
            "6ef34979-9123-4c30-8804-3b863c64c113",
            "e848b471-f922-4d23-a427-668c47ce1629",
            "b3f13f2f-d2d4-4e15-8e06-5c9f822ec712"
        ],
        "steps": [
            {
                "name": "Step 1",
                "description": "A generic description"
            },
            {
                "name": "Step 2",
                "description": "A generic description"
            },
            {
                "name": "Step 3",
                "description": "A generic description"
            },
            {
                "name": "Step 4",
                "description": "A generic description"
            },
            {
                "name": "Step 5",
                "description": "A generic description"
            },
            {
                "name": "Step 6",
                "description": "A generic description"
            },
            {
                "name": "Step 7",
                "description": "A generic description"
            }
        ]
    }
]